[
    {
        "name": "Hoang Minh Tien",
        "score": 5,
        "time": "2022-02-05 23:59 | Category: Ebony, size 2 meters",
        "description":
            "Photos and videos are for the purpose of collecting coins only. But the item is also very beautiful, so buy it, everyone, Photos and videos are for the purpose of collecting coins only. But the item is also very beautiful, so buy it, everyone",
        "listImg": []
    },
    {
        "name": "Lam Thien Toan",
        "score": 4,
        "time": "2022-02-05 23:59 | Category: Ebony, size 2 meters",
        "description":
            "Photos and videos are for the purpose of collecting coins only. But the item is also very beautiful, so buy it, everyone",
        "listImg": []
    },
    {
        "name": "Tran Hoang Duy",
        "score": 3,
        "time": "2022-02-05 23:59 | Category: Ebony, size 2 meters",
        "description":
            "Photos and videos are for the purpose of collecting coins only. But the item is also very beautiful, so buy it, everyone",
        "listImg": []
    },
    {
        "name": "Ngo Tien Dat",
        "score": 2,
        "time": "2022-02-05 23:59 | Category: Ebony, size 2 meters",
        "description":
            "Photos and videos are for the purpose of collecting coins only. But the item is also very beautiful, so buy it, everyone",
        "listImg": []
    },
    {
        "name": "Mai Duc Long",
        "score": 1,
        "time": "2022-02-05 23:59 | Category: Ebony, size 2 meters",
        "description":
            "",
        "listImg": [
            "https://i.imgur.com/5EtVc9Y.png",
            "https://i.imgur.com/pkyKkCi.png",
            "https://i.imgur.com/xgjF3lk.png"
        ]
    },
    {
        "name": "Ngo Duc Tri",
        "score": 3,
        "time": "2022-02-05 23:59 | Category: Ebony, size 2 meters",
        "description":
            "",
        "listImg": [
            "https://i.imgur.com/5EtVc9Y.png",
            "https://i.imgur.com/pkyKkCi.png",
            "https://i.imgur.com/xgjF3lk.png"
        ]
    },
    {
        "name": "Nguyen Huy Phuc",
        "score": 5,
        "time": "2022-02-05 23:59 | Category: Ebony, size 2 meters",
        "description":
            "",
        "listImg": [
            "https://i.imgur.com/5EtVc9Y.png",
            "https://i.imgur.com/pkyKkCi.png",
            "https://i.imgur.com/xgjF3lk.png"
        ]
    },
    {
        "name": "Nguyen Trung Kien",
        "score": 1,
        "time": "2022-02-05 23:59 | Category: Ebony, size 2 meters",
        "description":
            "",
        "listImg": [
            "https://i.imgur.com/5EtVc9Y.png",
            "https://i.imgur.com/pkyKkCi.png",
            "https://i.imgur.com/xgjF3lk.png"
        ]
    },
    {
        "name": "Nguyen Truong Hai Dang",
        "score": 2,
        "time": "2022-02-05 23:59 | Category: Ebony, size 2 meters",
        "description":
            "",
        "listImg": [
            "https://i.imgur.com/5EtVc9Y.png",
            "https://i.imgur.com/pkyKkCi.png",
            "https://i.imgur.com/xgjF3lk.png"
        ]
    },
    {
        "name": "Ho Van Hoa",
        "score": 4,
        "time": "2022-02-05 23:59 | Category: Ebony, size 2 meters",
        "description":
            "",
        "listImg": [
            "https://i.imgur.com/5EtVc9Y.png",
            "https://i.imgur.com/pkyKkCi.png",
            "https://i.imgur.com/xgjF3lk.png"
        ]
    },
    {
        "name": "Tran Van Thai",
        "score": 4,
        "time": "2022-02-05 23:59 | Category: Ebony, size 2 meters",
        "description":
            "Photos and videos are for the purpose of collecting coins only. But the item is also very beautiful, so buy it, everyone",
        "listImg": [
            "https://i.imgur.com/5EtVc9Y.png",
            "https://i.imgur.com/pkyKkCi.png",
            "https://i.imgur.com/xgjF3lk.png"
        ]
    },
    {
        "name": "Le Minh Hoang",
        "score": 1,
        "time": "2022-02-05 23:59 | Category: Ebony, size 2 meters",
        "description":
            "Photos and videos are for the purpose of collecting coins only. But the item is also very beautiful, so buy it, everyone",
        "listImg": [
            "https://i.imgur.com/5EtVc9Y.png",
            "https://i.imgur.com/pkyKkCi.png",
            "https://i.imgur.com/xgjF3lk.png"
        ]
    },
    {
        "name": "Le Nguyen Minh Hieu",
        "score": 3,
        "time": "2022-02-05 23:59 | Category: Ebony, size 2 meters",
        "description":
            "Photos and videos are for the purpose of collecting coins only. But the item is also very beautiful, so buy it, everyone",
        "listImg": [
            "https://i.imgur.com/5EtVc9Y.png",
            "https://i.imgur.com/pkyKkCi.png",
            "https://i.imgur.com/xgjF3lk.png"
        ]
    },
    {
        "name": "Vo Hong Phuc",
        "score": 2,
        "time": "2022-02-05 23:59 | Category: Ebony, size 2 meters",
        "description":
            "Photos and videos are for the purpose of collecting coins only. But the item is also very beautiful, so buy it, everyone",
        "listImg": [
            "https://i.imgur.com/5EtVc9Y.png",
            "https://i.imgur.com/pkyKkCi.png",
            "https://i.imgur.com/xgjF3lk.png"
        ]
    },
    {
        "name": "Le Cong Luc",
        "score": 5,
        "time": "2022-02-05 23:59 | Category: Ebony, size 2 meters",
        "description":
            "Photos and videos are for the purpose of collecting coins only. But the item is also very beautiful, so buy it, everyone",
        "listImg": [
            "https://i.imgur.com/5EtVc9Y.png",
            "https://i.imgur.com/pkyKkCi.png",
            "https://i.imgur.com/xgjF3lk.png"
        ]
    },
    {
        "name": "Lam Minh Nhat",
        "score": 5,
        "time": "2022-02-05 23:59 | Category: Ebony, size 2 meters",
        "description":
            "Photos and videos are for the purpose of collecting coins only. But the item is also very beautiful, so buy it, everyone, Photos and videos are for the purpose of collecting coins only. But the item is also very beautiful, so buy it, everyone",
        "listImg": [
            "https://i.imgur.com/5EtVc9Y.png",
            "https://i.imgur.com/pkyKkCi.png",
            "https://i.imgur.com/xgjF3lk.png"
        ]
    },
    {
        "name": "Nguyen Duy Uyen",
        "score": 4,
        "time": "2022-02-05 23:59 | Category: Ebony, size 2 meters",
        "description":
            "Photos and videos are for the purpose of collecting coins only. But the item is also very beautiful, so buy it, everyone",
        "listImg": [
            "https://i.imgur.com/5EtVc9Y.png",
            "https://i.imgur.com/pkyKkCi.png",
            "https://i.imgur.com/xgjF3lk.png"
        ]
    },
    {
        "name": "Nguyen Tran Ngoc Lien",
        "score": 3,
        "time": "2022-02-05 23:59 | Category: Ebony, size 2 meters",
        "description":
            "Photos and videos are for the purpose of collecting coins only. But the item is also very beautiful, so buy it, everyone",
        "listImg": [
            "https://i.imgur.com/5EtVc9Y.png",
            "https://i.imgur.com/pkyKkCi.png",
            "https://i.imgur.com/xgjF3lk.png"
        ]
    },
    {
        "name": "Bui Huu Tien Dat",
        "score": 2,
        "time": "2022-02-05 23:59 | Category: Ebony, size 2 meters",
        "description":
            "Photos and videos are for the purpose of collecting coins only. But the item is also very beautiful, so buy it, everyone",
        "listImg": [
            "https://i.imgur.com/5EtVc9Y.png",
            "https://i.imgur.com/pkyKkCi.png",
            "https://i.imgur.com/xgjF3lk.png"
        ]
    }
]